CHANGES.rst
CONTRIBUTORS.rst
MANIFEST.in
README.rst
TODO.txt
setup.cfg
setup.py
src/plone/__init__.py
src/plone.recipe.precompiler.egg-info/PKG-INFO
src/plone.recipe.precompiler.egg-info/SOURCES.txt
src/plone.recipe.precompiler.egg-info/dependency_links.txt
src/plone.recipe.precompiler.egg-info/entry_points.txt
src/plone.recipe.precompiler.egg-info/namespace_packages.txt
src/plone.recipe.precompiler.egg-info/not-zip-safe
src/plone.recipe.precompiler.egg-info/requires.txt
src/plone.recipe.precompiler.egg-info/top_level.txt
src/plone/recipe/__init__.py
src/plone/recipe/precompiler/__init__.py