Metadata-Version: 1.1
Name: plone.recipe.precompiler
Version: 0.7.2
Summary: zc.buildout recipe to precompile python and po files.
Home-page: https://github.com/plone/plone.recipe.precompiler
Author: Steve McMahon
Author-email: steve@dcn.org
License: GPL v 2
Keywords: buildout
Platform: UNKNOWN
Classifier: Development Status :: 5 - Production/Stable
Classifier: Intended Audience :: Developers
Classifier: Intended Audience :: System Administrators
Classifier: License :: OSI Approved :: GNU General Public License (GPL)
Classifier: Operating System :: OS Independent
Classifier: Programming Language :: Python
Classifier: Programming Language :: Python :: 2.7
Classifier: Programming Language :: Python :: 3.6
Classifier: Programming Language :: Python :: 3.7
Classifier: Framework :: Buildout
